<annotation>
	<folder>label5</folder>
	<filename>20220816DJI_0620_14.JPG</filename>
	<path>C:\Users\cjh19\Desktop\label5\20220816DJI_0620_14.JPG</path>
	<source>
		<database>Unknown</database>
	</source>
	<size>
		<width>1024</width>
		<height>1024</height>
		<depth>3</depth>
	</size>
	<segmented>0</segmented>
	<object>
		<name>Tassel</name>
		<pose>Unspecified</pose>
		<truncated>0</truncated>
		<difficult>0</difficult>
		<bndbox>
			<xmin>324</xmin>
			<ymin>174</ymin>
			<xmax>374</xmax>
			<ymax>210</ymax>
		</bndbox>
	</object>
	<object>
		<name>Tassel</name>
		<pose>Unspecified</pose>
		<truncated>1</truncated>
		<difficult>0</difficult>
		<bndbox>
			<xmin>922</xmin>
			<ymin>560</ymin>
			<xmax>1024</xmax>
			<ymax>680</ymax>
		</bndbox>
	</object>
	<object>
		<name>Tassel</name>
		<pose>Unspecified</pose>
		<truncated>0</truncated>
		<difficult>0</difficult>
		<bndbox>
			<xmin>795</xmin>
			<ymin>647</ymin>
			<xmax>833</xmax>
			<ymax>729</ymax>
		</bndbox>
	</object>
	<object>
		<name>Tassel</name>
		<pose>Unspecified</pose>
		<truncated>0</truncated>
		<difficult>0</difficult>
		<bndbox>
			<xmin>653</xmin>
			<ymin>585</ymin>
			<xmax>683</xmax>
			<ymax>608</ymax>
		</bndbox>
	</object>
	<object>
		<name>Tassel</name>
		<pose>Unspecified</pose>
		<truncated>0</truncated>
		<difficult>0</difficult>
		<bndbox>
			<xmin>58</xmin>
			<ymin>185</ymin>
			<xmax>95</xmax>
			<ymax>208</ymax>
		</bndbox>
	</object>
	<object>
		<name>Tassel</name>
		<pose>Unspecified</pose>
		<truncated>0</truncated>
		<difficult>0</difficult>
		<bndbox>
			<xmin>121</xmin>
			<ymin>576</ymin>
			<xmax>145</xmax>
			<ymax>609</ymax>
		</bndbox>
	</object>
	<object>
		<name>Tassel</name>
		<pose>Unspecified</pose>
		<truncated>1</truncated>
		<difficult>0</difficult>
		<bndbox>
			<xmin>98</xmin>
			<ymin>981</ymin>
			<xmax>182</xmax>
			<ymax>1024</ymax>
		</bndbox>
	</object>
	<object>
		<name>Tassel</name>
		<pose>Unspecified</pose>
		<truncated>1</truncated>
		<difficult>0</difficult>
		<bndbox>
			<xmin>166</xmin>
			<ymin>932</ymin>
			<xmax>281</xmax>
			<ymax>1024</ymax>
		</bndbox>
	</object>
	<object>
		<name>Tassel</name>
		<pose>Unspecified</pose>
		<truncated>1</truncated>
		<difficult>0</difficult>
		<bndbox>
			<xmin>323</xmin>
			<ymin>960</ymin>
			<xmax>393</xmax>
			<ymax>1024</ymax>
		</bndbox>
	</object>
</annotation>
