<annotation>
	<folder>JPEGImages</folder>
	<filename>20220813DJI_0522_21.JPG</filename>
	<path>F:\05&#21338;&#22763;\01&#21338;&#19968;&#19978;&#23398;&#26399;\&#29577;&#31859;&#25277;&#31319;&#35782;&#21035;\2022_maize_picture\magic_2_rgb\label\JPEGImages\20220813DJI_0522_21.JPG</path>
	<source>
		<database>Unknown</database>
	</source>
	<size>
		<width>1024</width>
		<height>1024</height>
		<depth>3</depth>
	</size>
	<segmented>0</segmented>
	<object>
		<name>Tassel</name>
		<pose>Unspecified</pose>
		<truncated>0</truncated>
		<difficult>0</difficult>
		<bndbox>
			<xmin>943</xmin>
			<ymin>250</ymin>
			<xmax>978</xmax>
			<ymax>325</ymax>
		</bndbox>
	</object>
	<object>
		<name>Tassel</name>
		<pose>Unspecified</pose>
		<truncated>0</truncated>
		<difficult>0</difficult>
		<bndbox>
			<xmin>399</xmin>
			<ymin>204</ymin>
			<xmax>440</xmax>
			<ymax>254</ymax>
		</bndbox>
	</object>
</annotation>