<annotation>
	<folder>JPEGImages</folder>
	<filename>20220813DJI_0495_7.JPG</filename>
	<path>C:\Users\cjh19\Desktop\magic_2_rgb\label\JPEGImages\20220813DJI_0495_7.JPG</path>
	<source>
		<database>Unknown</database>
	</source>
	<size>
		<width>1024</width>
		<height>1024</height>
		<depth>3</depth>
	</size>
	<segmented>0</segmented>
	<object>
		<name>Tassel</name>
		<pose>Unspecified</pose>
		<truncated>0</truncated>
		<difficult>0</difficult>
		<bndbox>
			<xmin>886</xmin>
			<ymin>777</ymin>
			<xmax>982</xmax>
			<ymax>854</ymax>
		</bndbox>
	</object>
	<object>
		<name>Tassel</name>
		<pose>Unspecified</pose>
		<truncated>0</truncated>
		<difficult>0</difficult>
		<bndbox>
			<xmin>38</xmin>
			<ymin>626</ymin>
			<xmax>111</xmax>
			<ymax>671</ymax>
		</bndbox>
	</object>
	<object>
		<name>Tassel</name>
		<pose>Unspecified</pose>
		<truncated>0</truncated>
		<difficult>0</difficult>
		<bndbox>
			<xmin>860</xmin>
			<ymin>386</ymin>
			<xmax>951</xmax>
			<ymax>468</ymax>
		</bndbox>
	</object>
	<object>
		<name>Tassel</name>
		<pose>Unspecified</pose>
		<truncated>0</truncated>
		<difficult>0</difficult>
		<bndbox>
			<xmin>312</xmin>
			<ymin>352</ymin>
			<xmax>446</xmax>
			<ymax>459</ymax>
		</bndbox>
	</object>
</annotation>